OrzMC/__init__.py
OrzMC/app/Client.py
OrzMC/app/Config.py
OrzMC/app/Console.py
OrzMC/app/Constants.py
OrzMC/app/Daemon.py
OrzMC/app/Downloader.py
OrzMC/app/Game.py
OrzMC/app/Nginx.py
OrzMC/app/OrzMC.py
OrzMC/app/Plugins.py
OrzMC/app/Server.py
OrzMC/app/SkinSystem.py
OrzMC/app/Tools.py
OrzMC/app/Version.py
OrzMC/app/__init__.py
OrzMC/core/BMCLAPI.py
OrzMC/core/Fabric.py
OrzMC/core/Forge.py
OrzMC/core/Mojang.py
OrzMC/core/OptiFine.py
OrzMC/core/Oracle.py
OrzMC/core/PaperAPI.py
OrzMC/core/Spigot.py
OrzMC/core/__init__.py
OrzMC/utils/CleanUp.py
OrzMC/utils/ColorString.py
OrzMC/utils/RichText.py
OrzMC/utils/__init__.py
OrzMC/utils/utils.py
OrzMC-1.0.118.dist-info/LICENSE
OrzMC-1.0.118.dist-info/METADATA
OrzMC-1.0.118.dist-info/WHEEL
OrzMC-1.0.118.dist-info/entry_points.txt
OrzMC-1.0.118.dist-info/top_level.txt
OrzMC-1.0.118.dist-info/RECORD
