Metadata-Version: 2.1
Name: OrzMC
Version: 1.0.118
Summary: A project for deployment of minecraft game.
Home-page: https://github.com/OrzGeeker/OrzMC.git
Author: 王志舟<wangzhizhou>
Author-email: 824219521@qq.com
Maintainer: 王志舟
Maintainer-email: 824219521@qq.com
Keywords: minecraft python
Platform: all
Classifier: Programming Language :: Python :: 3.6
Classifier: Programming Language :: Python :: 3.7
Classifier: License :: OSI Approved :: Apache Software License
Classifier: Operating System :: MacOS
Classifier: Operating System :: POSIX :: Linux
Requires-Python: >=3, <4
License-File: LICENSE
Requires-Dist: requests
Requires-Dist: twine
Requires-Dist: beautifulsoup4
Requires-Dist: pyyaml
Requires-Dist: tqdm
Requires-Dist: rich
